basedb/__init__.py
basedb/_version.py
basedb/column.py
basedb/database.py
basedb/row.py
basedb/table.py
ja_basedb-0.0.15.dist-info/LICENSE.txt
ja_basedb-0.0.15.dist-info/METADATA
ja_basedb-0.0.15.dist-info/WHEEL
ja_basedb-0.0.15.dist-info/top_level.txt
ja_basedb-0.0.15.dist-info/RECORD
